litellm_cz_etl/__init__.py
litellm_cz_etl/analysis.py
litellm_cz_etl/cli.py
litellm_cz_etl/database.py
litellm_cz_etl/output.py
litellm_cz_etl/transform.py
litellm_cz_etl-0.1.0.dist-info/WHEEL
litellm_cz_etl-0.1.0.dist-info/entry_points.txt
litellm_cz_etl-0.1.0.dist-info/METADATA
litellm_cz_etl-0.1.0.dist-info/RECORD
