Metadata-Version: 2.3
Name: litellm-cz-etl
Version: 0.1.0
Summary: Transform LiteLLM database data into CloudZero AnyCost CBF format
Author: Erik Peterson
Author-email: Erik Peterson <erik@cloudzero.com>
Requires-Dist: psycopg2-binary>=2.9.0
Requires-Dist: polars>=0.20.0
Requires-Dist: httpx>=0.25.0
Requires-Dist: click>=8.1.0
Requires-Dist: connectorx>=0.3.0
Requires-Python: >=3.12
